invenio_cli/__init__.py
invenio_cli/errors.py
invenio_cli/cli/__init__.py
invenio_cli/cli/assets.py
invenio_cli/cli/cli.py
invenio_cli/cli/containers.py
invenio_cli/cli/install.py
invenio_cli/cli/packages.py
invenio_cli/cli/services.py
invenio_cli/cli/translations.py
invenio_cli/cli/utils.py
invenio_cli/commands/__init__.py
invenio_cli/commands/assets.py
invenio_cli/commands/commands.py
invenio_cli/commands/containers.py
invenio_cli/commands/install.py
invenio_cli/commands/local.py
invenio_cli/commands/packages.py
invenio_cli/commands/requirements.py
invenio_cli/commands/services.py
invenio_cli/commands/services_health.py
invenio_cli/commands/steps.py
invenio_cli/commands/translations.py
invenio_cli/commands/upgrade.py
invenio_cli/helpers/__init__.py
invenio_cli/helpers/cli_config.py
invenio_cli/helpers/cookiecutter_wrapper.py
invenio_cli/helpers/docker_helper.py
invenio_cli/helpers/env.py
invenio_cli/helpers/filesystem.py
invenio_cli/helpers/package_managers.py
invenio_cli/helpers/process.py
invenio_cli/helpers/versions.py
invenio_cli-1.9.2.dist-info/licenses/AUTHORS.rst
invenio_cli-1.9.2.dist-info/licenses/LICENSE
invenio_cli-1.9.2.dist-info/METADATA
invenio_cli-1.9.2.dist-info/WHEEL
invenio_cli-1.9.2.dist-info/entry_points.txt
invenio_cli-1.9.2.dist-info/top_level.txt
invenio_cli-1.9.2.dist-info/RECORD
