Metadata-Version: 2.4
Name: invenio-cli
Version: 1.9.2
Summary: "Invenio module to ease the creation and management of applications."
Home-page: https://github.com/inveniosoftware/invenio-cli
Author: CERN & Northwestern University
Author-email: info@inveniosoftware.org
License: MIT
Keywords: invenio-cli
Platform: any
Classifier: Development Status :: 5 - Production/Stable
Requires-Python: >=3.7
License-File: LICENSE
License-File: AUTHORS.rst
Requires-Dist: Babel>=2.8
Requires-Dist: cookiecutter>=2.0.0
Requires-Dist: click>=7.1.1
Requires-Dist: click-default-group>=1.2.2
Requires-Dist: docker>=7.1.0
Requires-Dist: pipfile>=0.0.2
Requires-Dist: pipenv>=2024.0.3
Requires-Dist: PyYAML>=5.1.2
Requires-Dist: pynpm>=0.3.0
Requires-Dist: virtualenv>=20.0.35
Requires-Dist: tomli>=1.1.0; python_version < "3.11"
Provides-Extra: tests
Requires-Dist: pytest-black>=0.6.0; extra == "tests"
Requires-Dist: pytest-invenio>=1.4.0; extra == "tests"
Requires-Dist: Sphinx>=4.2.0; extra == "tests"
Dynamic: license-file
